islenska/bindb.py
islenska/bincompress.py
islenska/_bin.abi3.so
islenska/__init__.py
islenska/bin.cpp
islenska/dawgdictionary.cpp
islenska/dawgdictionary.h
islenska/bin_build.py
islenska/bincompress.h
islenska/basics.py
islenska/settings.py
islenska/py.typed
islenska/dawgdictionary.py
islenska/bincompress.cpp
islenska/bin.h
islenska/config/Prefs.conf
islenska/config/BinPackage.conf
islenska/config/BinErrata.conf
islenska/config/Adjectives.conf
islenska/resources/ordalisti-suffixes.dawg.bin
islenska/resources/compressed.bin
islenska/resources/ordalisti-prefixes.dawg.bin
islenska/resources/ordalisti-all.dawg.bin
islenska-1.1.1.dist-info/zip-safe
islenska-1.1.1.dist-info/RECORD
islenska-1.1.1.dist-info/WHEEL
islenska-1.1.1.dist-info/top_level.txt
islenska-1.1.1.dist-info/METADATA
islenska-1.1.1.dist-info/licenses/LICENSE
